braze/__init__.py
braze/client.py
braze_client-2.3.3.dist-info/LICENSE
braze_client-2.3.3.dist-info/METADATA
braze_client-2.3.3.dist-info/WHEEL
braze_client-2.3.3.dist-info/top_level.txt
braze_client-2.3.3.dist-info/RECORD
