Metadata-Version: 2.1
Name: braze-client
Version: 2.3.3
Summary: Braze Python Client
Home-page: https://github.com/dtatarkin/braze-client
Author-email: mail@dtatarkin.ru
Keywords: Appboy,Braze
Classifier: Programming Language :: Python
Classifier: Programming Language :: Python :: 2.7
Classifier: Programming Language :: Python :: 3.6
Classifier: Programming Language :: Python :: 3.7
Classifier: Programming Language :: Python :: 3.8
Classifier: Programming Language :: Python :: 3.9
Classifier: Programming Language :: Python :: 3.10
Requires-Python: >=2.7, !=3.0.*, !=3.1.*, !=3.2.*, !=3.3.*, !=3.4.*, !=3.5.*
License-File: LICENSE
Requires-Dist: requests (<3.0.0,>=2.21.0)
Requires-Dist: tenacity (<6.0.0,>=5.0.0)
Provides-Extra: dev
Requires-Dist: tox ; extra == 'dev'
